{
  "AC": [
    "Ascension Island",
    "AS"
  ],
  "AF": [
    "Afghanistan",
    "AS"
  ],
  "AX": [
    "Aland Islands",
    "EU"
  ],
  "AL": [
    "Albania",
    "EU"
  ],
  "DZ": [
    "Algeria",
    "AF"
  ],
  "AS": [
    "American Samoa",
    "OC",
    "USD",
    "$"
  ],
  "AD": [
    "Andorra",
    "EU"
  ],
  "AO": [
    "Angola",
    "AF"
  ],
  "AI": [
    "Anguilla",
    "NA"
  ],
  "AQ": [
    "Antarctica",
    "OC"
  ],
  "AG": [
    "Antigua & Barbuda",
    "NA"
  ],
  "AR": [
    "Argentina",
    "SA"
  ],
  "AM": [
    "Armenia",
    "AS"
  ],
  "AW": [
    "Aruba",
    "NA"
  ],
  "AU": [
    "Australia",
    "OC",
    "AUD",
    "A$"
  ],
  "AT": [
    "Austria",
    "EU"
  ],
  "AZ": [
    "Azerbaijan",
    "AS"
  ],
  "BS": [
    "Bahamas",
    "NA"
  ],
  "BH": [
    "Bahrain",
    "AS"
  ],
  "BD": [
    "Bangladesh",
    "AS"
  ],
  "BB": [
    "Barbados",
    "NA"
  ],
  "BY": [
    "Belarus",
    "EU"
  ],
  "BE": [
    "Belgium",
    "EU"
  ],
  "BZ": [
    "Belize",
    "NA"
  ],
  "BJ": [
    "Benin",
    "AF"
  ],
  "BM": [
    "Bermuda",
    "NA"
  ],
  "BT": [
    "Bhutan",
    "AS"
  ],
  "BO": [
    "Bolivia",
    "SA"
  ],
  "BQ": [
    "Caribbean Netherlands",
    "NA"
  ],
  "BA": [
    "Bosnia & Herzegovina",
    "EU"
  ],
  "BW": [
    "Botswana",
    "AF"
  ],
  "BV": [
    "Bouvet Island",
    "OC"
  ],
  "BR": [
    "Brazil",
    "SA",
    "BRL",
    "R$"
  ],
  "IO": [
    "British Indian Ocean Territory",
    "AS",
    "USD",
    "$"
  ],
  "BN": [
    "Brunei",
    "AS"
  ],
  "BG": [
    "Bulgaria",
    "EU"
  ],
  "BF": [
    "Burkina Faso",
    "AF"
  ],
  "BI": [
    "Burundi",
    "AF"
  ],
  "KH": [
    "Cambodia",
    "AS"
  ],
  "CM": [
    "Cameroon",
    "AF"
  ],
  "CA": [
    "Canada",
    "NA",
    "CAD",
    "C$"
  ],
  "CV": [
    "Cape Verde",
    "AF"
  ],
  "KY": [
    "Cayman Islands",
    "NA"
  ],
  "CF": [
    "Central African Republic",
    "AF"
  ],
  "TA": [
    "Tristan da Cunha",
    "AF"
  ],
  "TD": [
    "Chad",
    "AF"
  ],
  "CL": [
    "Chile",
    "SA"
  ],
  "CN": [
    "China",
    "AS",
    "CNY",
    "¥"
  ],
  "CX": [
    "Christmas Island",
    "AS",
    "AUD",
    "A$"
  ],
  "CC": [
    "Cocos (Keeling) Islands",
    "AS",
    "AUD",
    "A$"
  ],
  "CO": [
    "Colombia",
    "SA"
  ],
  "KM": [
    "Comoros",
    "AF"
  ],
  "CG": [
    "Congo - Brazzaville",
    "AF"
  ],
  "CD": [
    "Congo - Kinshasa",
    "AF"
  ],
  "CK": [
    "Cook Islands",
    "OC"
  ],
  "CR": [
    "Costa Rica",
    "NA"
  ],
  "CI": [
    "Cote d'Ivoire",
    "AF"
  ],
  "HR": [
    "Croatia",
    "EU"
  ],
  "CU": [
    "Cuba",
    "NA"
  ],
  "CW": [
    "Curaçao",
    "NA"
  ],
  "CY": [
    "Cyprus",
    "EU"
  ],
  "CZ": [
    "Czechia",
    "EU"
  ],
  "DK": [
    "Denmark",
    "EU"
  ],
  "DJ": [
    "Djibouti",
    "AF"
  ],
  "DM": [
    "Dominica",
    "NA"
  ],
  "DO": [
    "Dominican Republic",
    "NA"
  ],
  "EC": [
    "Ecuador",
    "SA",
    "USD",
    "$"
  ],
  "EG": [
    "Egypt",
    "AF"
  ],
  "SV": [
    "El Salvador",
    "NA",
    "USD",
    "$"
  ],
  "GQ": [
    "Equatorial Guinea",
    "AF"
  ],
  "ER": [
    "Eritrea",
    "AF"
  ],
  "EE": [
    "Estonia",
    "EU"
  ],
  "ET": [
    "Ethiopia",
    "AF"
  ],
  "FK": [
    "Falkland Islands",
    "SA"
  ],
  "FO": [
    "Faroe Islands",
    "EU"
  ],
  "FJ": [
    "Fiji",
    "OC"
  ],
  "FI": [
    "Finland",
    "EU"
  ],
  "FR": [
    "France",
    "EU"
  ],
  "GF": [
    "French Guiana",
    "SA"
  ],
  "PF": [
    "French Polynesia",
    "OC"
  ],
  "TF": [
    "French Southern Territories",
    "OC"
  ],
  "GA": [
    "Gabon",
    "AF"
  ],
  "GM": [
    "Gambia",
    "AF"
  ],
  "GE": [
    "Georgia",
    "AS"
  ],
  "DE": [
    "Germany",
    "EU"
  ],
  "GH": [
    "Ghana",
    "AF"
  ],
  "GI": [
    "Gibraltar",
    "EU"
  ],
  "GR": [
    "Greece",
    "EU"
  ],
  "GL": [
    "Greenland",
    "NA",
    "DKK",
    "KR"
  ],
  "GD": [
    "Grenada",
    "NA"
  ],
  "GP": [
    "Guadeloupe",
    "NA"
  ],
  "GU": [
    "Guam",
    "OC",
    "USD",
    "$"
  ],
  "GT": [
    "Guatemala",
    "NA"
  ],
  "GG": [
    "Guernsey",
    "EU"
  ],
  "GN": [
    "Guinea",
    "AF"
  ],
  "GW": [
    "Guinea-Bissau",
    "AF"
  ],
  "GY": [
    "Guyana",
    "SA"
  ],
  "HT": [
    "Haiti",
    "NA"
  ],
  "HM": [
    "Heard Island and McDonald Islands",
    "OC",
    "AUD",
    "A$"
  ],
  "VA": [
    "Vatican City",
    "EU"
  ],
  "HN": [
    "Honduras",
    "NA"
  ],
  "HK": [
    "Hong Kong SAR China",
    "AS",
    "HKD",
    "HK$"
  ],
  "HU": [
    "Hungary",
    "EU"
  ],
  "IS": [
    "Iceland",
    "EU"
  ],
  "IN": [
    "India",
    "AS",
    "INR",
    "₹"
  ],
  "ID": [
    "Indonesia",
    "AS",
    "IDR",
    "Rp"
  ],
  "IR": [
    "Islamic Republic of Iran",
    "AS"
  ],
  "IQ": [
    "Iraq",
    "AS"
  ],
  "IE": [
    "Ireland",
    "EU"
  ],
  "IM": [
    "Isle of Man",
    "EU"
  ],
  "IL": [
    "Israel",
    "AS",
    "ILS",
    "₪"
  ],
  "IT": [
    "Italy",
    "EU"
  ],
  "JM": [
    "Jamaica",
    "NA"
  ],
  "JP": [
    "Japan",
    "AS",
    "JPY",
    "¥"
  ],
  "JE": [
    "Jersey",
    "EU"
  ],
  "JO": [
    "Jordan",
    "AS"
  ],
  "KZ": [
    "Kazakhstan",
    "AS"
  ],
  "KE": [
    "Kenya",
    "AF"
  ],
  "KI": [
    "Kiribati",
    "OC"
  ],
  "KP": [
    "Democratic People's Republic of Korea",
    "AS"
  ],
  "KR": [
    "South Korea",
    "AS",
    "KRW",
    "₩"
  ],
  "KW": [
    "Kuwait",
    "AS"
  ],
  "KG": [
    "Kyrgyzstan",
    "AS"
  ],
  "LA": [
    "Laos",
    "AS"
  ],
  "LV": [
    "Latvia",
    "EU"
  ],
  "LB": [
    "Lebanon",
    "AS"
  ],
  "LS": [
    "Lesotho",
    "AF"
  ],
  "LR": [
    "Liberia",
    "AF"
  ],
  "LY": [
    "Libya",
    "AF"
  ],
  "LI": [
    "Liechtenstein",
    "EU"
  ],
  "LT": [
    "Lithuania",
    "EU"
  ],
  "LU": [
    "Luxembourg",
    "EU"
  ],
  "MO": [
    "Macao SAR China",
    "AS"
  ],
  "MK": [
    "North Macedonia",
    "EU"
  ],
  "MG": [
    "Madagascar",
    "AF"
  ],
  "MW": [
    "Malawi",
    "AF"
  ],
  "MY": [
    "Malaysia",
    "AS",
    "MYR",
    "RM"
  ],
  "MV": [
    "Maldives",
    "AS"
  ],
  "ML": [
    "Mali",
    "AF"
  ],
  "MT": [
    "Malta",
    "EU"
  ],
  "MH": [
    "Marshall Islands",
    "OC",
    "USD",
    "$"
  ],
  "MQ": [
    "Martinique",
    "NA"
  ],
  "MR": [
    "Mauritania",
    "AF"
  ],
  "MU": [
    "Mauritius",
    "AF"
  ],
  "YT": [
    "Mayotte",
    "AF"
  ],
  "MX": [
    "Mexico",
    "NA",
    "MXN",
    "MEX$"
  ],
  "FM": [
    "Federated States of Micronesia",
    "OC",
    "USD",
    "$"
  ],
  "MD": [
    "Moldova",
    "EU"
  ],
  "MC": [
    "Monaco",
    "EU"
  ],
  "MN": [
    "Mongolia",
    "AS"
  ],
  "ME": [
    "Montenegro",
    "EU"
  ],
  "MS": [
    "Montserrat",
    "NA"
  ],
  "MA": [
    "Morocco",
    "AF"
  ],
  "MZ": [
    "Mozambique",
    "AF"
  ],
  "MM": [
    "Myanmar (Burma)",
    "AS"
  ],
  "NA": [
    "Namibia",
    "AF"
  ],
  "NR": [
    "Nauru",
    "OC",
    "AUD",
    "A$"
  ],
  "NP": [
    "Nepal",
    "AS"
  ],
  "NL": [
    "Netherlands",
    "EU"
  ],
  "NC": [
    "New Caledonia",
    "OC"
  ],
  "NZ": [
    "New Zealand",
    "OC",
    "AUD",
    "A$"
  ],
  "NI": [
    "Nicaragua",
    "NA"
  ],
  "NE": [
    "Niger",
    "AF"
  ],
  "NG": [
    "Nigeria",
    "AF"
  ],
  "NU": [
    "Niue",
    "OC"
  ],
  "NF": [
    "Norfolk Island",
    "OC",
    "AUD",
    "A$"
  ],
  "MP": [
    "Northern Mariana Islands",
    "OC",
    "USD",
    "$"
  ],
  "NO": [
    "Norway",
    "EU"
  ],
  "OM": [
    "Oman",
    "AS"
  ],
  "PK": [
    "Pakistan",
    "AS"
  ],
  "PW": [
    "Palau",
    "OC",
    "USD",
    "$"
  ],
  "PS": [
    "Palestinian Territories",
    "AS",
    "ILS",
    "₪"
  ],
  "PA": [
    "Panama",
    "NA"
  ],
  "PG": [
    "Papua New Guinea",
    "OC"
  ],
  "PY": [
    "Paraguay",
    "SA"
  ],
  "PE": [
    "Peru",
    "SA"
  ],
  "PH": [
    "Philippines",
    "AS",
    "PHP",
    "₱"
  ],
  "PN": [
    "Pitcairn Islands",
    "OC"
  ],
  "PL": [
    "Poland",
    "EU"
  ],
  "PT": [
    "Portugal",
    "EU"
  ],
  "PR": [
    "Puerto Rico",
    "NA",
    "USD",
    "$"
  ],
  "QA": [
    "Qatar",
    "AS"
  ],
  "RE": [
    "Reunion",
    "AF"
  ],
  "RO": [
    "Romania",
    "EU"
  ],
  "RU": [
    "Russia",
    "AS",
    "RUB",
    "₽"
  ],
  "RW": [
    "Rwanda",
    "AF"
  ],
  "BL": [
    "St Barthelemy",
    "NA"
  ],
  "SH": [
    "St Helena",
    "AF"
  ],
  "KN": [
    "St Kitts & Nevis",
    "NA"
  ],
  "LC": [
    "St Lucia",
    "NA"
  ],
  "MF": [
    "St Martin",
    "NA"
  ],
  "PM": [
    "St Pierre & Miquelon",
    "NA"
  ],
  "VC": [
    "St Vincent & Grenadines",
    "NA"
  ],
  "WS": [
    "Samoa",
    "OC"
  ],
  "SM": [
    "San Marino",
    "EU"
  ],
  "ST": [
    "Sao Tome & Principe",
    "AF"
  ],
  "SA": [
    "Saudi Arabia",
    "AS",
    "SR",
    "SR"
  ],
  "SN": [
    "Senegal",
    "AF"
  ],
  "RS": [
    "Serbia",
    "EU"
  ],
  "SC": [
    "Seychelles",
    "AF"
  ],
  "SL": [
    "Sierra Leone",
    "AF"
  ],
  "SG": [
    "Singapore",
    "AS",
    "SGD",
    "S$"
  ],
  "SX": [
    "Sint Maarten",
    "NA"
  ],
  "SK": [
    "Slovakia",
    "EU"
  ],
  "SI": [
    "Slovenia",
    "EU"
  ],
  "SB": [
    "Solomon Islands",
    "OC"
  ],
  "SO": [
    "Somalia",
    "AF"
  ],
  "ZA": [
    "South Africa",
    "AF",
    "ZAR",
    "R"
  ],
  "GS": [
    "South Georgia & South Sandwich Islands",
    "SA",
    "GBP",
    "£"
  ],
  "SS": [
    "South Sudan",
    "AF"
  ],
  "ES": [
    "Spain",
    "EU"
  ],
  "LK": [
    "Sri Lanka",
    "AS"
  ],
  "SD": [
    "Sudan",
    "AF"
  ],
  "SR": [
    "Suriname",
    "SA"
  ],
  "SJ": [
    "Svalbard & Jan Mayen",
    "EU"
  ],
  "SZ": [
    "Eswatini",
    "AF"
  ],
  "SE": [
    "Sweden",
    "EU"
  ],
  "CH": [
    "Switzerland",
    "EU"
  ],
  "SY": [
    "Syrian Arab Republic",
    "AS"
  ],
  "TW": [
    "Taiwan",
    "AS"
  ],
  "TJ": [
    "Tajikistan",
    "AS"
  ],
  "TZ": [
    "Tanzania",
    "AF"
  ],
  "TH": [
    "Thailand",
    "AS",
    "THB",
    "฿"
  ],
  "TL": [
    "Timor-Leste",
    "AS",
    "USD",
    "$"
  ],
  "TG": [
    "Togo",
    "AF"
  ],
  "TK": [
    "Tokelau",
    "OC"
  ],
  "TO": [
    "Tonga",
    "OC"
  ],
  "TT": [
    "Trinidad & Tobago",
    "NA"
  ],
  "TN": [
    "Tunisia",
    "AF"
  ],
  "TR": [
    "Turkey",
    "AS",
    "TRY",
    "₺"
  ],
  "TM": [
    "Turkmenistan",
    "AS"
  ],
  "TC": [
    "Turks & Caicos Islands",
    "NA",
    "USD",
    "$"
  ],
  "TV": [
    "Tuvalu",
    "OC"
  ],
  "UG": [
    "Uganda",
    "AF"
  ],
  "UA": [
    "Ukraine",
    "EU"
  ],
  "AE": [
    "United Arab Emirates",
    "AS"
  ],
  "GB": [
    "United Kingdom",
    "EU",
    "GBP",
    "£"
  ],
  "US": [
    "United States",
    "NA",
    "USD",
    "$"
  ],
  "UM": [
    "United States Minor Outlying Islands",
    "NA"
  ],
  "UY": [
    "Uruguay",
    "SA"
  ],
  "UZ": [
    "Uzbekistan",
    "AS"
  ],
  "VU": [
    "Vanuatu",
    "OC"
  ],
  "VE": [
    "Venezuela",
    "SA"
  ],
  "VN": [
    "Vietnam",
    "AS"
  ],
  "VG": [
    "British Virgin Islands",
    "NA",
    "USD",
    "$"
  ],
  "VI": [
    "Virgin Islands, U.S.",
    "NA",
    "USD",
    "$"
  ],
  "WF": [
    "Wallis & Futuna",
    "OC"
  ],
  "EH": [
    "Western Sahara",
    "AF"
  ],
  "XK": [
    "Kosovo",
    "EU"
  ],
  "YE": [
    "Yemen",
    "AS"
  ],
  "ZM": [
    "Zambia",
    "AF"
  ],
  "ZW": [
    "Zimbabwe",
    "AF"
  ]
}